csvkit/__init__.py
csvkit/cleanup.py
csvkit/cli.py
csvkit/exceptions.py
csvkit/grep.py
csvkit/convert/__init__.py
csvkit/convert/fixed.py
csvkit/convert/geojs.py
csvkit/utilities/__init__.py
csvkit/utilities/csvclean.py
csvkit/utilities/csvcut.py
csvkit/utilities/csvformat.py
csvkit/utilities/csvgrep.py
csvkit/utilities/csvjoin.py
csvkit/utilities/csvjson.py
csvkit/utilities/csvlook.py
csvkit/utilities/csvpy.py
csvkit/utilities/csvsort.py
csvkit/utilities/csvsql.py
csvkit/utilities/csvstack.py
csvkit/utilities/csvstat.py
csvkit/utilities/in2csv.py
csvkit/utilities/sql2csv.py
csvkit-2.2.0.data/data/share/man/man1/csvclean.1
csvkit-2.2.0.data/data/share/man/man1/csvcut.1
csvkit-2.2.0.data/data/share/man/man1/csvformat.1
csvkit-2.2.0.data/data/share/man/man1/csvgrep.1
csvkit-2.2.0.data/data/share/man/man1/csvjoin.1
csvkit-2.2.0.data/data/share/man/man1/csvjson.1
csvkit-2.2.0.data/data/share/man/man1/csvlook.1
csvkit-2.2.0.data/data/share/man/man1/csvpy.1
csvkit-2.2.0.data/data/share/man/man1/csvsort.1
csvkit-2.2.0.data/data/share/man/man1/csvsql.1
csvkit-2.2.0.data/data/share/man/man1/csvstack.1
csvkit-2.2.0.data/data/share/man/man1/csvstat.1
csvkit-2.2.0.data/data/share/man/man1/in2csv.1
csvkit-2.2.0.data/data/share/man/man1/sql2csv.1
csvkit-2.2.0.dist-info/licenses/AUTHORS.rst
csvkit-2.2.0.dist-info/licenses/COPYING
csvkit-2.2.0.dist-info/METADATA
csvkit-2.2.0.dist-info/WHEEL
csvkit-2.2.0.dist-info/entry_points.txt
csvkit-2.2.0.dist-info/top_level.txt
csvkit-2.2.0.dist-info/RECORD
